boilerpy3/__init__.py
boilerpy3/document.py
boilerpy3/exceptions.py
boilerpy3/extractors.py
boilerpy3/filters.py
boilerpy3/marker.py
boilerpy3/parser.py
boilerpy3-1.0.6.dist-info/LICENSE
boilerpy3-1.0.6.dist-info/METADATA
boilerpy3-1.0.6.dist-info/WHEEL
boilerpy3-1.0.6.dist-info/top_level.txt
boilerpy3-1.0.6.dist-info/RECORD
