Metadata-Version: 2.1
Name: boilerpy3
Version: 1.0.6
Summary: Python port of Boilerpipe, for HTML boilerplate removal and text extraction
Home-page: https://github.com/jmriebold/BoilerPy3
Author: John Riebold
Author-email: jmriebold@gmail.com
License: Apache 2.0
Keywords: boilerpipe,boilerpy,html text extraction,text extraction,full text extraction
Platform: UNKNOWN
Classifier: Development Status :: 4 - Beta
Classifier: Topic :: Utilities
Classifier: License :: OSI Approved :: Apache Software License
Classifier: Programming Language :: Python :: 3
Classifier: Programming Language :: Python :: 3.6
Classifier: Programming Language :: Python :: 3.7
Classifier: Programming Language :: Python :: 3.8
Classifier: Programming Language :: Python :: 3.9
Classifier: Programming Language :: Python :: 3.10
Requires-Python: >=3.6.*
